pysims/__init__.py
pysims/cli/__init__.py
pysims/cli/_base.py
pysims/cli/config.py
pysims/cli/main.py
PySIMS-0.0.1.dist-info/LICENSE
PySIMS-0.0.1.dist-info/METADATA
PySIMS-0.0.1.dist-info/WHEEL
PySIMS-0.0.1.dist-info/entry_points.txt
PySIMS-0.0.1.dist-info/top_level.txt
PySIMS-0.0.1.dist-info/RECORD
