Metadata-Version: 2.1
Name: PySIMS
Version: 0.0.1
Summary: The CLI for managing IoT sensors and meter data.
Author-email: Anton Lydell <antoningenjoren@gmail.com>
License: MIT License        
Project-URL: Bug Tracker, https://github.com/antonlydell/PySIMS/issues
Project-URL: Documentation, https://github.com/antonlydell/PySIMS
Project-URL: Source Code, https://github.com/antonlydell/PySIMS
Keywords: Sensors,IoT,LoRaWAN
Classifier: Development Status :: 1 - Planning
Classifier: Environment :: Console
Classifier: Intended Audience :: End Users/Desktop
Classifier: Intended Audience :: Information Technology
Classifier: Intended Audience :: Science/Research
Classifier: License :: OSI Approved :: MIT License
Classifier: Operating System :: OS Independent
Classifier: Programming Language :: Python :: 3 :: Only
Classifier: Programming Language :: Python :: 3.10
Classifier: Topic :: Home Automation
Classifier: Topic :: Scientific/Engineering
Classifier: Topic :: Utilities
Requires-Python: >=3.10
License-File: LICENSE
Requires-Dist: click (>=8.0)
Requires-Dist: pandas (>=1.3)
Requires-Dist: pandemy (>=1.1)
Requires-Dist: requests (>=2.26)
Requires-Dist: toml (>=0.10)
